blyss_verifier/__init__.py
blyss_verifier/verify.py
blyss_verifier/data/OVMF_v0.0.1.fd
blyss_verifier/data/__init__.py
blyss_verifier/data/test_claims.json
blyss_verifier/data/test_claims_2_direct.txt
blyss_verifier/data/test_full_attestation.json
blyss_verifier/data/test_full_attestation_2.json
blyss_verifier/protocol/__init__.py
blyss_verifier/protocol/v0.0.1-test.json
blyss_verifier/protocol/v0.0.1.json
blyss_verifier-0.1.8.dist-info/LICENSE.txt
blyss_verifier-0.1.8.dist-info/METADATA
blyss_verifier-0.1.8.dist-info/WHEEL
blyss_verifier-0.1.8.dist-info/top_level.txt
blyss_verifier-0.1.8.dist-info/RECORD
