Metadata-Version: 2.1
Name: blyss-verifier
Version: 0.1.8
Summary: A verifier for the Blyss Confidential AI service
Author-email: Samir Menon <samir@blyss.dev>, Neil Movva <neil@blyss.dev>
Project-URL: Homepage, https://github.com/blyssprivacy/verifier
Classifier: Programming Language :: Python :: 3
Classifier: License :: OSI Approved :: MIT License
Classifier: Operating System :: OS Independent
Requires-Python: >=3.9
License-File: LICENSE.txt
Requires-Dist: sev-snp-measure ==0.0.7
Requires-Dist: sev-attest-tool ==0.2.4
Requires-Dist: ctutlz ==0.9.8
Requires-Dist: pyOpenSSL ==23.3.0
